guardrails_api_client/__init__.py
guardrails_api_client/api_client.py
guardrails_api_client/api_response.py
guardrails_api_client/configuration.py
guardrails_api_client/exceptions.py
guardrails_api_client/openapi-spec.json
guardrails_api_client/py.typed
guardrails_api_client/rest.py
guardrails_api_client/api/__init__.py
guardrails_api_client/api/guard_api.py
guardrails_api_client/api/openai_api.py
guardrails_api_client/api/service_health_api.py
guardrails_api_client/api/validate_api.py
guardrails_api_client/models/__init__.py
guardrails_api_client/models/any_type.py
guardrails_api_client/models/applicator.py
guardrails_api_client/models/args_and_kwargs.py
guardrails_api_client/models/arrays_inner.py
guardrails_api_client/models/call.py
guardrails_api_client/models/call_inputs.py
guardrails_api_client/models/content.py
guardrails_api_client/models/core.py
guardrails_api_client/models/error_span.py
guardrails_api_client/models/fail_result.py
guardrails_api_client/models/format_annotation.py
guardrails_api_client/models/guard.py
guardrails_api_client/models/health_check.py
guardrails_api_client/models/http_error.py
guardrails_api_client/models/inputs.py
guardrails_api_client/models/iteration.py
guardrails_api_client/models/llm_resource.py
guardrails_api_client/models/llm_response.py
guardrails_api_client/models/meta_data.py
guardrails_api_client/models/model_schema.py
guardrails_api_client/models/open_ai_chat_completion.py
guardrails_api_client/models/open_ai_chat_completion_payload.py
guardrails_api_client/models/open_ai_chat_completion_payload_messages_inner.py
guardrails_api_client/models/outputs.py
guardrails_api_client/models/outputs_parsed_output.py
guardrails_api_client/models/outputs_validation_response.py
guardrails_api_client/models/pass_result.py
guardrails_api_client/models/primitives.py
guardrails_api_client/models/reask.py
guardrails_api_client/models/simple_types.py
guardrails_api_client/models/unevaluated.py
guardrails_api_client-0.3.13.dist-info/LICENSE
guardrails_api_client-0.3.13.dist-info/METADATA
guardrails_api_client-0.3.13.dist-info/WHEEL
guardrails_api_client-0.3.13.dist-info/top_level.txt
guardrails_api_client-0.3.13.dist-info/RECORD
