Metadata-Version: 2.1
Name: guardrails-api-client
Version: 0.3.13
Summary: Guardrails API Client.
Author-email: Guardrails AI <contact@guardrailsai.com>
License: Apache License
Keywords: Guardrails,Guardrails AI,Guardrails API,Guardrails API Client
Requires-Python: >=3.8, <4
License-File: LICENSE
Requires-Dist: python-dateutil >=2.5.3
Requires-Dist: setuptools >=21.0.0
Requires-Dist: urllib3 <2.1.0,>=1.25.3
Requires-Dist: pydantic >=2
Requires-Dist: typing-extensions >=4.7.1
Provides-Extra: dev
Requires-Dist: pyright ; extra == 'dev'
Requires-Dist: pytest ; extra == 'dev'
Requires-Dist: pytest-cov ; extra == 'dev'
Requires-Dist: ruff ; extra == 'dev'
